monobinpy/__init__.py
monobinpy/_helpers.py
monobinpy/cum_bin.py
monobinpy/iso_bin.py
monobinpy/ndr_bin.py
monobinpy/pct_bin.py
monobinpy/sts_bin.py
monobinpy/woe_bin.py
monobinpy-0.0.1.dist-info/LICENSE
monobinpy-0.0.1.dist-info/METADATA
monobinpy-0.0.1.dist-info/WHEEL
monobinpy-0.0.1.dist-info/top_level.txt
monobinpy-0.0.1.dist-info/RECORD
