Metadata-Version: 2.1
Name: monobinpy
Version: 0.0.1
Summary: Monotonic Binning for Credit Rating Models
Author-email: Andrija Djurovic <djandrija@gmail.com>
License: MIT License        
Project-URL: repository, https://github.com/andrija-djurovic/monobinpy
Classifier: License :: OSI Approved :: MIT License
Classifier: Programming Language :: Python
Classifier: Programming Language :: Python :: 3
Requires-Python: >=3.0
License-File: LICENSE
Requires-Dist: numpy
Requires-Dist: pandas
Requires-Dist: scipy
Requires-Dist: scikit-learn
Requires-Dist: statsmodels
Provides-Extra: build
Requires-Dist: build ; extra == 'build'
Requires-Dist: twine ; extra == 'build'
